mistralai/__init__.py
mistralai/async_client.py
mistralai/client.py
mistralai/client_base.py
mistralai/constants.py
mistralai/exceptions.py
mistralai/models/__init__.py
mistralai/models/chat_completion.py
mistralai/models/common.py
mistralai/models/embeddings.py
mistralai/models/models.py
mistralai/py.typed
eidolon_ai_mistralai-0.1.6a0.dist-info/LICENSE
eidolon_ai_mistralai-0.1.6a0.dist-info/METADATA
eidolon_ai_mistralai-0.1.6a0.dist-info/WHEEL
eidolon_ai_mistralai-0.1.6a0.dist-info/RECORD
