Metadata-Version: 2.1
Name: eidolon-ai-mistralai
Version: 0.1.6a0
Summary: 
Author: Bam4d
Author-email: bam4d@mistral.ai
Requires-Python: >=3.9,<4.0
Classifier: Programming Language :: Python :: 3
Classifier: Programming Language :: Python :: 3.9
Classifier: Programming Language :: Python :: 3.10
Classifier: Programming Language :: Python :: 3.11
Classifier: Programming Language :: Python :: 3.12
Requires-Dist: httpx (<1)
Requires-Dist: orjson (>=3.9.10,<4.0.0)
Requires-Dist: pydantic (>=2.5.2,<3.0.0)
